[
  {
    "id": "7183616a-c5dd-4e41-ad4d-eab6678c026f",
    "data": [
      {
        "text": "so who invented you",
        "userDefined": false
      }
    ],
    "isTemplate": false,
    "count": 0,
    "lang": "en",
    "updated": 0
  },
  {
    "id": "92bcade6-0b28-4f6c-b2e5-1c9b51d1c8dd",
    "data": [
      {
        "text": "what\u0027s the name ",
        "userDefined": false
      },
      {
        "text": "of",
        "userDefined": false
      },
      {
        "text": " ",
        "userDefined": false
      },
      {
        "text": "your",
        "userDefined": false
      },
      {
        "text": " programmer",
        "userDefined": false
      }
    ],
    "isTemplate": false,
    "count": 0,
    "lang": "en",
    "updated": 0
  },
  {
    "id": "afa80df6-d5b7-48f6-a17b-294ff48fd329",
    "data": [
      {
        "text": "who is ",
        "userDefined": false
      },
      {
        "text": "your",
        "userDefined": false
      },
      {
        "text": " teacher",
        "userDefined": false
      }
    ],
    "isTemplate": false,
    "count": 0,
    "lang": "en",
    "updated": 0
  },
  {
    "id": "3adc81ee-46b6-4bc5-b1d4-deda77ba89e4",
    "data": [
      {
        "text": "and who create you",
        "userDefined": false
      }
    ],
    "isTemplate": false,
    "count": 0,
    "lang": "en",
    "updated": 0
  },
  {
    "id": "af76185a-cbfe-456c-9492-bcb357549825",
    "data": [
      {
        "text": "who made ",
        "userDefined": false
      },
      {
        "text": "your application",
        "userDefined": false
      }
    ],
    "isTemplate": false,
    "count": 0,
    "lang": "en",
    "updated": 0
  },
  {
    "id": "1c40db42-539f-4217-81de-0f981ee38012",
    "data": [
      {
        "text": "what is ",
        "userDefined": false
      },
      {
        "text": "your",
        "userDefined": false
      },
      {
        "text": " makers name",
        "userDefined": false
      }
    ],
    "isTemplate": false,
    "count": 0,
    "lang": "en",
    "updated": 0
  },
  {
    "id": "a66ac909-5f0e-4098-a020-8c801e7e2e1c",
    "data": [
      {
        "text": "so who created you",
        "userDefined": false
      }
    ],
    "isTemplate": false,
    "count": 0,
    "lang": "en",
    "updated": 0
  },
  {
    "id": "e52da306-81f1-4caf-9f2c-3a525f23bca2",
    "data": [
      {
        "text": "can you tell me who created you",
        "userDefined": false
      }
    ],
    "isTemplate": false,
    "count": 0,
    "lang": "en",
    "updated": 0
  },
  {
    "id": "eaea84b2-b1ab-40a8-8a06-0270ac8dd6d6",
    "data": [
      {
        "text": "who was ",
        "userDefined": false
      },
      {
        "text": "your",
        "userDefined": false
      },
      {
        "text": " founder",
        "userDefined": false
      }
    ],
    "isTemplate": false,
    "count": 0,
    "lang": "en",
    "updated": 0
  },
  {
    "id": "f8022d91-1a69-4ea0-a3d3-04391c6ac391",
    "data": [
      {
        "text": "do you know ",
        "userDefined": false
      },
      {
        "text": "your",
        "userDefined": false
      },
      {
        "text": " creators",
        "userDefined": false
      }
    ],
    "isTemplate": false,
    "count": 0,
    "lang": "en",
    "updated": 0
  },
  {
    "id": "24e05fea-1eb1-4b59-b06f-18270bf30919",
    "data": [
      {
        "text": "who is ",
        "userDefined": false
      },
      {
        "text": "your",
        "userDefined": false
      },
      {
        "text": " creator",
        "userDefined": false
      }
    ],
    "isTemplate": false,
    "count": 0,
    "lang": "en",
    "updated": 0
  },
  {
    "id": "3877d4e4-6fca-42f7-be4f-2115859d79c8",
    "data": [
      {
        "text": "I said who developed you",
        "userDefined": false
      }
    ],
    "isTemplate": false,
    "count": 0,
    "lang": "en",
    "updated": 0
  },
  {
    "id": "35e791a1-5f2d-4891-8b4b-78210552ed1a",
    "data": [
      {
        "text": "I want to know the names ",
        "userDefined": false
      },
      {
        "text": "of",
        "userDefined": false
      },
      {
        "text": " ",
        "userDefined": false
      },
      {
        "text": "your",
        "userDefined": false
      },
      {
        "text": " developers",
        "userDefined": false
      }
    ],
    "isTemplate": false,
    "count": 0,
    "lang": "en",
    "updated": 0
  },
  {
    "id": "2ea8ee1f-0013-4d0a-b660-4684c1a275ee",
    "data": [
      {
        "text": "what is ",
        "userDefined": false
      },
      {
        "text": "your",
        "userDefined": false
      },
      {
        "text": " creator name",
        "userDefined": false
      }
    ],
    "isTemplate": false,
    "count": 0,
    "lang": "en",
    "updated": 0
  },
  {
    "id": "5f0bb768-2517-427e-8474-f5cf309f8ad6",
    "data": [
      {
        "text": "I mean who made ",
        "userDefined": false
      },
      {
        "text": "this application",
        "userDefined": false
      }
    ],
    "isTemplate": false,
    "count": 0,
    "lang": "en",
    "updated": 0
  },
  {
    "id": "44041d35-c253-4db6-aa78-89eba4648305",
    "data": [
      {
        "text": "I said who made ",
        "userDefined": false
      },
      {
        "text": "your",
        "userDefined": false
      },
      {
        "text": " program",
        "userDefined": false
      }
    ],
    "isTemplate": false,
    "count": 0,
    "lang": "en",
    "updated": 0
  },
  {
    "id": "f49be9c4-3197-4d4c-b509-7e288be32187",
    "data": [
      {
        "text": "what is the name ",
        "userDefined": false
      },
      {
        "text": "of",
        "userDefined": false
      },
      {
        "text": " ",
        "userDefined": false
      },
      {
        "text": "your",
        "userDefined": false
      },
      {
        "text": " developer",
        "userDefined": false
      }
    ],
    "isTemplate": false,
    "count": 0,
    "lang": "en",
    "updated": 0
  },
  {
    "id": "2e844523-51e5-4a8f-b334-5a1c90cf4b44",
    "data": [
      {
        "text": "so who is ",
        "userDefined": false
      },
      {
        "text": "your",
        "userDefined": false
      },
      {
        "text": " developer",
        "userDefined": false
      }
    ],
    "isTemplate": false,
    "count": 0,
    "lang": "en",
    "updated": 0
  },
  {
    "id": "2664f94c-140e-4b2f-8a0f-571bce8ff62d",
    "data": [
      {
        "text": "who was ",
        "userDefined": false
      },
      {
        "text": "your",
        "userDefined": false
      },
      {
        "text": " inventor",
        "userDefined": false
      }
    ],
    "isTemplate": false,
    "count": 0,
    "lang": "en",
    "updated": 0
  },
  {
    "id": "90b2a0a6-fdc3-419c-9109-aad8e8310ee2",
    "data": [
      {
        "text": "what is ",
        "userDefined": false
      },
      {
        "text": "your",
        "userDefined": false
      },
      {
        "text": " developers name",
        "userDefined": false
      }
    ],
    "isTemplate": false,
    "count": 0,
    "lang": "en",
    "updated": 0
  },
  {
    "id": "2929c234-013d-48c1-b9e4-82fcca714723",
    "data": [
      {
        "text": "do you know ",
        "userDefined": false
      },
      {
        "text": "your",
        "userDefined": false
      },
      {
        "text": " maker",
        "userDefined": false
      }
    ],
    "isTemplate": false,
    "count": 0,
    "lang": "en",
    "updated": 0
  },
  {
    "id": "c338c51d-6a92-44c3-ac31-af2872227fa2",
    "data": [
      {
        "text": "can you tell me something about ",
        "userDefined": false
      },
      {
        "text": "your",
        "userDefined": false
      },
      {
        "text": " creators",
        "userDefined": false
      }
    ],
    "isTemplate": false,
    "count": 0,
    "lang": "en",
    "updated": 0
  },
  {
    "id": "e507ef7a-01cd-4720-9ddc-f9cc0a2c2bbe",
    "data": [
      {
        "text": "your",
        "userDefined": false
      },
      {
        "text": " developers",
        "userDefined": false
      }
    ],
    "isTemplate": false,
    "count": 0,
    "lang": "en",
    "updated": 0
  },
  {
    "id": "c5632ab3-41bd-442e-8b27-f358a6535153",
    "data": [
      {
        "text": "I said who ",
        "userDefined": false
      },
      {
        "text": "are",
        "userDefined": false
      },
      {
        "text": " ",
        "userDefined": false
      },
      {
        "text": "your",
        "userDefined": false
      },
      {
        "text": " creators",
        "userDefined": false
      }
    ],
    "isTemplate": false,
    "count": 0,
    "lang": "en",
    "updated": 0
  },
  {
    "id": "e8397467-ba4e-495d-aabe-30a50e5a4197",
    "data": [
      {
        "text": "what company made you",
        "userDefined": false
      }
    ],
    "isTemplate": false,
    "count": 0,
    "lang": "en",
    "updated": 0
  },
  {
    "id": "7339658d-2a5d-42ca-abd3-ab313d8c108a",
    "data": [
      {
        "text": "who did create you",
        "userDefined": false
      }
    ],
    "isTemplate": false,
    "count": 0,
    "lang": "en",
    "updated": 0
  },
  {
    "id": "a663863b-a8c4-41d8-a394-c6ccf815c951",
    "data": [
      {
        "text": "what is ",
        "userDefined": false
      },
      {
        "text": "your",
        "userDefined": false
      },
      {
        "text": " developer name",
        "userDefined": false
      }
    ],
    "isTemplate": false,
    "count": 0,
    "lang": "en",
    "updated": 0
  },
  {
    "id": "b1c2e6b5-112f-48c1-8da2-1ae0fa15a1e2",
    "data": [
      {
        "text": "do you know who makes you",
        "userDefined": false
      }
    ],
    "isTemplate": false,
    "count": 0,
    "lang": "en",
    "updated": 0
  },
  {
    "id": "33d2612f-7183-47d5-b2e7-a6cc906851f5",
    "data": [
      {
        "text": "who made you",
        "userDefined": false
      }
    ],
    "isTemplate": false,
    "count": 1,
    "lang": "en",
    "updated": 0
  },
  {
    "id": "07df62dc-a18e-45a0-9ff9-278d80483bca",
    "data": [
      {
        "text": "what is ",
        "userDefined": false
      },
      {
        "text": "your",
        "userDefined": false
      },
      {
        "text": " teachers name",
        "userDefined": false
      }
    ],
    "isTemplate": false,
    "count": 0,
    "lang": "en",
    "updated": 0
  },
  {
    "id": "23fd5a1c-9ecd-4c93-bbf7-dcb3ab52dfe5",
    "data": [
      {
        "text": "what\u0027s the name ",
        "userDefined": false
      },
      {
        "text": "of",
        "userDefined": false
      },
      {
        "text": " ",
        "userDefined": false
      },
      {
        "text": "your",
        "userDefined": false
      },
      {
        "text": " creators",
        "userDefined": false
      }
    ],
    "isTemplate": false,
    "count": 0,
    "lang": "en",
    "updated": 0
  },
  {
    "id": "007aad9d-bd70-4c0a-8fd1-1a60057a1f6d",
    "data": [
      {
        "text": "who is ",
        "userDefined": false
      },
      {
        "text": "your",
        "userDefined": false
      },
      {
        "text": " inventor",
        "userDefined": false
      }
    ],
    "isTemplate": false,
    "count": 0,
    "lang": "en",
    "updated": 0
  },
  {
    "id": "ac6a5fd1-7664-4e14-8750-b039dea6a95c",
    "data": [
      {
        "text": "so who made ",
        "userDefined": false
      },
      {
        "text": "this application",
        "userDefined": false
      }
    ],
    "isTemplate": false,
    "count": 0,
    "lang": "en",
    "updated": 0
  },
  {
    "id": "c74d5573-9342-4a18-b3c6-f31df053f728",
    "data": [
      {
        "text": "so who is ",
        "userDefined": false
      },
      {
        "text": "your",
        "userDefined": false
      },
      {
        "text": " creator",
        "userDefined": false
      }
    ],
    "isTemplate": false,
    "count": 0,
    "lang": "en",
    "updated": 0
  },
  {
    "id": "e7aee6e1-1874-4306-a022-dc6d6a266188",
    "data": [
      {
        "text": "who created you",
        "userDefined": false
      }
    ],
    "isTemplate": false,
    "count": 0,
    "lang": "en",
    "updated": 0
  },
  {
    "id": "14482500-346f-46af-bd51-adcd5baa89af",
    "data": [
      {
        "text": "your",
        "userDefined": false
      },
      {
        "text": " inventor",
        "userDefined": false
      }
    ],
    "isTemplate": false,
    "count": 0,
    "lang": "en",
    "updated": 0
  },
  {
    "id": "abcd376b-6f2b-4c63-b724-1bb542e0bc2a",
    "data": [
      {
        "text": "so who made you",
        "userDefined": false
      }
    ],
    "isTemplate": false,
    "count": 0,
    "lang": "en",
    "updated": 0
  },
  {
    "id": "169db7dc-d8cf-4c45-9720-24486cbf857a",
    "data": [
      {
        "text": "who",
        "userDefined": false
      },
      {
        "text": " is ",
        "userDefined": false
      },
      {
        "text": "your",
        "userDefined": false
      },
      {
        "text": " programmer",
        "userDefined": false
      }
    ],
    "isTemplate": false,
    "count": 0,
    "lang": "en",
    "updated": 0
  },
  {
    "id": "21d7bfb2-72c5-4b43-970d-8724fb33383a",
    "data": [
      {
        "text": "what is the name ",
        "userDefined": false
      },
      {
        "text": "of",
        "userDefined": false
      },
      {
        "text": " ",
        "userDefined": false
      },
      {
        "text": "your",
        "userDefined": false
      },
      {
        "text": " developers",
        "userDefined": false
      }
    ],
    "isTemplate": false,
    "count": 0,
    "lang": "en",
    "updated": 0
  },
  {
    "id": "a71473df-52ef-4379-86d8-a1f63179c0ca",
    "data": [
      {
        "text": "so who create you",
        "userDefined": false
      }
    ],
    "isTemplate": false,
    "count": 0,
    "lang": "en",
    "updated": 0
  },
  {
    "id": "d71642a4-4c8e-4964-bf80-d25f1a57db87",
    "data": [
      {
        "text": "who built you",
        "userDefined": false
      }
    ],
    "isTemplate": false,
    "count": 0,
    "lang": "en",
    "updated": 0
  },
  {
    "id": "3f2b7348-1bd4-40c5-9d74-5d56bb8d92fc",
    "data": [
      {
        "text": "your",
        "userDefined": false
      },
      {
        "text": " creator",
        "userDefined": false
      }
    ],
    "isTemplate": false,
    "count": 0,
    "lang": "en",
    "updated": 0
  },
  {
    "id": "75f20fb4-3ae8-4630-a78d-c0881faf6050",
    "data": [
      {
        "text": "I want know who made you",
        "userDefined": false
      }
    ],
    "isTemplate": false,
    "count": 0,
    "lang": "en",
    "updated": 0
  },
  {
    "id": "121918c3-0327-42d2-b088-e5640dc976cb",
    "data": [
      {
        "text": "do you know who created u",
        "userDefined": false
      }
    ],
    "isTemplate": false,
    "count": 0,
    "lang": "en",
    "updated": 0
  },
  {
    "id": "f8e6784d-1d51-4bea-abc0-f845b0c105ae",
    "data": [
      {
        "text": "I want to know who made you",
        "userDefined": false
      }
    ],
    "isTemplate": false,
    "count": 0,
    "lang": "en",
    "updated": 0
  },
  {
    "id": "958380f5-436b-45ea-beac-1591344bbad1",
    "data": [
      {
        "text": "what is ",
        "userDefined": false
      },
      {
        "text": "your",
        "userDefined": false
      },
      {
        "text": " creator\u0027s name",
        "userDefined": false
      }
    ],
    "isTemplate": false,
    "count": 0,
    "lang": "en",
    "updated": 0
  },
  {
    "id": "f14527ae-8535-4f5b-bee4-6a3a5ae3a522",
    "data": [
      {
        "text": "what\u0027s the name ",
        "userDefined": false
      },
      {
        "text": "of",
        "userDefined": false
      },
      {
        "text": " ",
        "userDefined": false
      },
      {
        "text": "your",
        "userDefined": false
      },
      {
        "text": " developer",
        "userDefined": false
      }
    ],
    "isTemplate": false,
    "count": 0,
    "lang": "en",
    "updated": 0
  },
  {
    "id": "c4741a97-10a5-4ad8-838f-ec2cd2870dfa",
    "data": [
      {
        "text": "your",
        "userDefined": false
      },
      {
        "text": " teacher",
        "userDefined": false
      }
    ],
    "isTemplate": false,
    "count": 0,
    "lang": "en",
    "updated": 0
  },
  {
    "id": "22c61b2e-81f5-4a4f-a9ae-75311c2bb91a",
    "data": [
      {
        "text": "what is the name ",
        "userDefined": false
      },
      {
        "text": "of",
        "userDefined": false
      },
      {
        "text": " ",
        "userDefined": false
      },
      {
        "text": "your",
        "userDefined": false
      },
      {
        "text": " creator",
        "userDefined": false
      }
    ],
    "isTemplate": false,
    "count": 0,
    "lang": "en",
    "updated": 0
  },
  {
    "id": "f50a4740-113e-48a4-8fec-aef6f0b1154f",
    "data": [
      {
        "text": "who invented you",
        "userDefined": false
      }
    ],
    "isTemplate": false,
    "count": 0,
    "lang": "en",
    "updated": 0
  },
  {
    "id": "b4fbdadb-2871-40cd-81aa-0c17fedf97d1",
    "data": [
      {
        "text": "what\u0027s the name ",
        "userDefined": false
      },
      {
        "text": "of",
        "userDefined": false
      },
      {
        "text": " ",
        "userDefined": false
      },
      {
        "text": "your",
        "userDefined": false
      },
      {
        "text": " creator",
        "userDefined": false
      }
    ],
    "isTemplate": false,
    "count": 0,
    "lang": "en",
    "updated": 0
  },
  {
    "id": "a921387d-9c09-458d-b58d-6387a55e0523",
    "data": [
      {
        "text": "do you know who created you",
        "userDefined": false
      }
    ],
    "isTemplate": false,
    "count": 0,
    "lang": "en",
    "updated": 0
  },
  {
    "id": "55e5ddc5-08ca-4a4b-865f-dd13e0d005cb",
    "data": [
      {
        "text": "tell me who is ",
        "userDefined": false
      },
      {
        "text": "your",
        "userDefined": false
      },
      {
        "text": " creator",
        "userDefined": false
      }
    ],
    "isTemplate": false,
    "count": 0,
    "lang": "en",
    "updated": 0
  },
  {
    "id": "57b16113-fc3c-4560-b490-92bdb6f1fb28",
    "data": [
      {
        "text": "who were ",
        "userDefined": false
      },
      {
        "text": "your",
        "userDefined": false
      },
      {
        "text": " creators",
        "userDefined": false
      }
    ],
    "isTemplate": false,
    "count": 0,
    "lang": "en",
    "updated": 0
  },
  {
    "id": "5ea0a45c-2760-4ce2-b104-a776b57c6839",
    "data": [
      {
        "text": "do you know who made you",
        "userDefined": false
      }
    ],
    "isTemplate": false,
    "count": 0,
    "lang": "en",
    "updated": 0
  },
  {
    "id": "ed5c6e65-f4b2-4dfb-98d9-1387a84d2bd2",
    "data": [
      {
        "text": "and who created you",
        "userDefined": false
      }
    ],
    "isTemplate": false,
    "count": 0,
    "lang": "en",
    "updated": 0
  },
  {
    "id": "d5aa2084-dabb-48ec-837d-0743406c3cfe",
    "data": [
      {
        "text": "who is ",
        "userDefined": false
      },
      {
        "text": "your",
        "userDefined": false
      },
      {
        "text": " developer",
        "userDefined": false
      }
    ],
    "isTemplate": false,
    "count": 0,
    "lang": "en",
    "updated": 0
  },
  {
    "id": "e24d93d8-3a76-426f-9eb9-3171b120f68c",
    "data": [
      {
        "text": "I said who made you tell me",
        "userDefined": false
      }
    ],
    "isTemplate": false,
    "count": 0,
    "lang": "en",
    "updated": 0
  }
]